LICENSE
MANIFEST.in
README.rst
setup.py
flanker/__init__.py
flanker/_email.py
flanker/dkim.py
flanker/metrics.py
flanker/utils.py
flanker.egg-info/PKG-INFO
flanker.egg-info/SOURCES.txt
flanker.egg-info/dependency_links.txt
flanker.egg-info/requires.txt
flanker.egg-info/top_level.txt
flanker.egg-info/zip-safe
flanker/addresslib/__init__.py
flanker/addresslib/address.py
flanker/addresslib/corrector.py
flanker/addresslib/quote.py
flanker/addresslib/validate.py
flanker/addresslib/_parser/__init__.py
flanker/addresslib/_parser/addr_spec_parsetab.py
flanker/addresslib/_parser/lexer.py
flanker/addresslib/_parser/mailbox_or_url_list_parsetab.py
flanker/addresslib/_parser/mailbox_or_url_parsetab.py
flanker/addresslib/_parser/mailbox_parsetab.py
flanker/addresslib/_parser/parser.py
flanker/addresslib/_parser/url_parsetab.py
flanker/addresslib/drivers/__init__.py
flanker/addresslib/drivers/dns_lookup.py
flanker/addresslib/drivers/redis_driver.py
flanker/addresslib/plugins/__init__.py
flanker/addresslib/plugins/_tokenizer.py
flanker/addresslib/plugins/aol.py
flanker/addresslib/plugins/gmail.py
flanker/addresslib/plugins/google.py
flanker/addresslib/plugins/hotmail.py
flanker/addresslib/plugins/icloud.py
flanker/addresslib/plugins/yahoo.py
flanker/mime/__init__.py
flanker/mime/bounce.py
flanker/mime/create.py
flanker/mime/message/__init__.py
flanker/mime/message/charsets.py
flanker/mime/message/errors.py
flanker/mime/message/part.py
flanker/mime/message/scanner.py
flanker/mime/message/threading.py
flanker/mime/message/utils.py
flanker/mime/message/fallback/__init__.py
flanker/mime/message/fallback/create.py
flanker/mime/message/fallback/part.py
flanker/mime/message/headers/__init__.py
flanker/mime/message/headers/encodedword.py
flanker/mime/message/headers/encoding.py
flanker/mime/message/headers/headers.py
flanker/mime/message/headers/parametrized.py
flanker/mime/message/headers/parsing.py
flanker/mime/message/headers/wrappers.py
tests/__init__.py
tests/dkim_test.py
tests/dummy_test.py
tests/email_test.py
tests/addresslib/__init__.py
tests/addresslib/address_test.py
tests/addresslib/corrector_test.py
tests/addresslib/external_dataset_test.py
